README.rst
setup.cfg
setup.py
torpeewee/__init__.py
torpeewee/model.py
torpeewee/mysql.py
torpeewee/postgresql.py
torpeewee/query.py
torpeewee/transaction.py
torpeewee.egg-info/PKG-INFO
torpeewee.egg-info/SOURCES.txt
torpeewee.egg-info/dependency_links.txt
torpeewee.egg-info/not-zip-safe
torpeewee.egg-info/requires.txt
torpeewee.egg-info/top_level.txt