Metadata-Version: 1.0
Name: torpeewee
Version: 0.0.7
Summary: Tornado asynchronous ORM by peewee
Home-page: https://github.com/snower/torpeewee
Author: ['snower']
Author-email: ['sujian199@gmail.com']
License: MIT
Keywords: tornado,mysql,postgresql,orm,tormysql,momoko
Platform: UNKNOWN
